crudhex/__init__.py
crudhex/__main__.py
crudhex/adapters/__init__.py
crudhex/adapters/application/__init__.py
crudhex/adapters/application/cli/__init__.py
crudhex/adapters/application/cli/commands/__init__.py
crudhex/adapters/application/cli/commands/create_project.py
crudhex/adapters/application/cli/commands/generate_crud.py
crudhex/adapters/application/cli/main.py
crudhex/adapters/application/cli/services/__init__.py
crudhex/adapters/application/cli/services/console_out_context.py
crudhex/adapters/application/cli/utils/__init__.py
crudhex/adapters/application/cli/utils/cli_helper.py
crudhex/adapters/infrastructure/__init__.py
crudhex/adapters/infrastructure/loader/__init__.py
crudhex/adapters/infrastructure/loader/fs_config_loader.py
crudhex/adapters/infrastructure/loader/fs_spec_loader.py
crudhex/adapters/infrastructure/loader/yaml_helper.py
crudhex/adapters/infrastructure/template_writer/__init__.py
crudhex/adapters/infrastructure/template_writer/adapters/__init__.py
crudhex/adapters/infrastructure/template_writer/adapters/db_code_writer.py
crudhex/adapters/infrastructure/template_writer/adapters/domain_code_writer.py
crudhex/adapters/infrastructure/template_writer/adapters/mapper_code_writer.py
crudhex/adapters/infrastructure/template_writer/adapters/rest_code_writer.py
crudhex/adapters/infrastructure/template_writer/config/__init__.py
crudhex/adapters/infrastructure/template_writer/config/template_config.py
crudhex/adapters/infrastructure/template_writer/services/__init__.py
crudhex/adapters/infrastructure/template_writer/services/inflect_engine.py
crudhex/adapters/infrastructure/template_writer/services/template_env.py
crudhex/adapters/infrastructure/template_writer/templates/db/adapter.jinja2
crudhex/adapters/infrastructure/template_writer/templates/db/entity.jinja2
crudhex/adapters/infrastructure/template_writer/templates/db/fragments/field.jinja2
crudhex/adapters/infrastructure/template_writer/templates/db/fragments/id_field.jinja2
crudhex-0.17.4.dist-info/METADATA
crudhex-0.17.4.dist-info/entry_points.txt
crudhex-0.17.4.dist-info/WHEEL
crudhex-0.17.4.dist-info/RECORD
