Metadata-Version: 2.1
Name: crudhex
Version: 0.17.4
Summary: Java/Spring CRUD code generator
Home-page: https://github.com/salpreh/crudhex
License: MIT
Author: salpreh
Author-email: salpreh.7@gmail.com
Requires-Python: >=3.7,<4.0
Classifier: Development Status :: 3 - Alpha
Classifier: Environment :: Console
Classifier: Intended Audience :: Developers
Classifier: License :: OSI Approved :: MIT License
Classifier: Programming Language :: Python
Classifier: Programming Language :: Python :: 3
Classifier: Programming Language :: Python :: 3.7
Classifier: Programming Language :: Python :: 3.8
Classifier: Programming Language :: Python :: 3.9
Classifier: Programming Language :: Python :: 3.10
Classifier: Programming Language :: Python :: 3.11
Classifier: Programming Language :: Python :: 3
Classifier: Programming Language :: Python :: 3.10
Classifier: Programming Language :: Python :: 3.7
Classifier: Programming Language :: Python :: 3.8
Classifier: Programming Language :: Python :: 3.9
Classifier: Topic :: Software Development
Classifier: Topic :: Terminals
Classifier: Topic :: Utilities
Classifier: Typing :: Typed
Provides-Extra: all
Provides-Extra: scaffolding
Requires-Dist: Jinja2 (>=3.1.2,<4.0.0)
Requires-Dist: PyYAML (>=6.0,<7.0)
Requires-Dist: cookiecutter (>=2.1.1,<3.0.0) ; extra == "all" or extra == "scaffolding"
Requires-Dist: inflect (>=6.0.0,<7.0.0)
Requires-Dist: typer[all] (>=0.6.1,<0.7.0)
Project-URL: Documentation, https://github.com/salpreh/crudhex
Project-URL: Repository, https://github.com/salpreh/crudhex
